{
	"admin": 
	[
		{
			"moduleName": "Update Profile",
			"moduleLink": "profileManagement"
		},
		{
			"moduleName": "User Management",
			"moduleLink": "userManagement"
		},

		{
			"moduleName": "Rooms Management",
			"moduleLink": "roomManagement"
		},

		{
			"moduleName": "Room Allotment",
			"moduleLink": "roomAllotment"
		},

		{
			"moduleName": "Approve Rents",
			"moduleLink": "approveRent"
		}
	],

	"tenant": 
	[
		{
			"moduleName": "Update Profile",
			"moduleLink": "profileManagement"
		}
	]
}